sendspin/__init__.py
sendspin/audio.py
sendspin/audio_connector.py
sendspin/cli.py
sendspin/discovery.py
sendspin/settings.py
sendspin/utils.py
sendspin/daemon/__init__.py
sendspin/daemon/daemon.py
sendspin/serve/__init__.py
sendspin/serve/server.py
sendspin/serve/source.py
sendspin/serve/web/__init__.py
sendspin/serve/web/app.js
sendspin/serve/web/index.html
sendspin/serve/web/styles.css
sendspin/tui/__init__.py
sendspin/tui/app.py
sendspin/tui/keyboard.py
sendspin/tui/ui.py
sendspin-3.0.0.dist-info/licenses/LICENSE
sendspin-3.0.0.dist-info/METADATA
sendspin-3.0.0.dist-info/WHEEL
sendspin-3.0.0.dist-info/entry_points.txt
sendspin-3.0.0.dist-info/top_level.txt
sendspin-3.0.0.dist-info/RECORD
