Metadata-Version: 2.4
Name: sendspin
Version: 3.0.0
Summary: Synchronized audio player for Sendspin servers
Author-email: Sendspin Protocol Authors <sendspin@openhomefoundation.org>
License: Apache-2.0
Project-URL: Homepage, https://github.com/Sendspin-Protocol/sendspin
Project-URL: Bug Tracker, https://github.com/Sendspin-Protocol/sendspin/issues
Classifier: Environment :: Console
Classifier: Programming Language :: Python :: 3.12
Classifier: Programming Language :: Python :: 3.13
Requires-Python: >=3.12
License-File: LICENSE
Requires-Dist: aiosendspin>=2.1.0
Requires-Dist: aiosendspin-mpris>=2.1.0
Requires-Dist: av>=14.0.0
Requires-Dist: numpy>=1.24.0
Requires-Dist: qrcode>=8.0
Requires-Dist: readchar>=4.0.0
Requires-Dist: rich>=13.0.0
Requires-Dist: sounddevice>=0.4.6
Provides-Extra: test
Requires-Dist: codespell==2.4.1; extra == "test"
Requires-Dist: mypy==1.18.2; extra == "test"
Requires-Dist: pre-commit==4.4.0; extra == "test"
Requires-Dist: pre-commit-hooks==6.0.0; extra == "test"
Requires-Dist: ruff==0.14.5; extra == "test"
Dynamic: license-file
